{
    "name": "Task",
    "fields": [
        {
            "fieldName": "title",
            "fieldType": "String"
        },
        {
            "fieldName": "description",
            "fieldType": "String"
        }
    ],
    "relationships": [],
    "changelogDate": "20200406154300",
    "javadoc": "Task entity.\\n@author The JHipster team.",
    "entityTableName": "task",
    "dto": "no",
    "pagination": "no",
    "service": "serviceImpl",
    "jpaMetamodelFiltering": false,
    "fluentMethods": true,
    "readOnly": false,
    "embedded": false,
    "clientRootFolder": "",
    "applications": "*"
}